megacom/__init__.py
megacom/__main__.py
megacom-0.1.2.dist-info/LICENSE
megacom-0.1.2.dist-info/METADATA
megacom-0.1.2.dist-info/WHEEL
megacom-0.1.2.dist-info/entry_points.txt
megacom-0.1.2.dist-info/top_level.txt
megacom-0.1.2.dist-info/RECORD
