Metadata-Version: 2.1
Name: megacom
Version: 0.1.2
Summary: Alternative console-based UART client
Home-page: https://git.lain.faith/haskal/megacom
Author: haskal
Author-email: haskal@awoo.systems
License: AGPLv3
Platform: UNKNOWN
Classifier: Programming Language :: Python :: 3
Classifier: License :: OSI Approved :: GNU Affero General Public License v3
Classifier: Operating System :: Unix
Classifier: Topic :: Software Development :: User Interfaces
Classifier: Topic :: System :: Hardware :: Hardware Drivers
Classifier: Topic :: Terminals :: Serial
Classifier: Topic :: Utilities
Classifier: Typing :: Typed
Requires-Python: >=3.9
License-File: LICENSE
Requires-Dist: pyserial
Requires-Dist: pyserial-asyncio
